cli_gwkokab/__init__.py
cli_gwkokab/batch_scatter2d.py
cli_gwkokab/batch_scatter3d.py
cli_gwkokab/chain_plot.py
cli_gwkokab/corner_overplot.py
cli_gwkokab/corner_plot.py
cli_gwkokab/ess_evolution_plot.py
cli_gwkokab/ess_plot.py
cli_gwkokab/hist_overplot.py
cli_gwkokab/joint_plot.py
cli_gwkokab/ppd_plot.py
cli_gwkokab/r_hat_plot.py
cli_gwkokab/scatter2d.py
cli_gwkokab/scatter3d.py
gwkokab/__init__.py
gwkokab/constants.py
gwkokab/errors.py
gwkokab/parameters.py
gwkokab/py.typed
gwkokab/cosmology/__init__.py
gwkokab/cosmology/_cosmology.py
gwkokab/cosmology/_planck.py
gwkokab/inference/__init__.py
gwkokab/inference/analyticallikelihood.py
gwkokab/inference/poissonlikelihood_flowMC.py
gwkokab/inference/poissonlikelihood_numpyro.py
gwkokab/inference/poissonlikelihood_utils.py
gwkokab/models/__init__.py
gwkokab/models/constraints.py
gwkokab/models/transformations.py
gwkokab/models/wrappers.py
gwkokab/models/hybrids/__init__.py
gwkokab/models/hybrids/_bp2pfull.py
gwkokab/models/hybrids/_bp2pmultispinfull.py
gwkokab/models/hybrids/_ncombination.py
gwkokab/models/hybrids/_npowerlawmgaussian.py
gwkokab/models/hybrids/_powerlawpeak.py
gwkokab/models/mass/__init__.py
gwkokab/models/mass/_bp2p.py
gwkokab/models/mass/_models.py
gwkokab/models/redshift/__init__.py
gwkokab/models/redshift/_models.py
gwkokab/models/spin/__init__.py
gwkokab/models/spin/_models.py
gwkokab/models/utils/__init__.py
gwkokab/models/utils/_doubletruncpowerlaw.py
gwkokab/models/utils/_extendedsupporttransformeddistribution.py
gwkokab/models/utils/_joindistribution.py
gwkokab/models/utils/_lazyjointdistribution.py
gwkokab/models/utils/_scaledmixture.py
gwkokab/poisson_mean/__init__.py
gwkokab/poisson_mean/_injection_based.py
gwkokab/poisson_mean/_neural_pdet.py
gwkokab/poisson_mean/_neural_vt.py
gwkokab/poisson_mean/poisson_factory.py
gwkokab/utils/__init__.py
gwkokab/utils/kernel.py
gwkokab/utils/math.py
gwkokab/utils/tools.py
gwkokab/utils/train.py
gwkokab/utils/transformations.py
gwkokab-0.2.1.dist-info/licenses/LICENSE
kokab/__init__.py
gwkokab-0.2.1.dist-info/METADATA
gwkokab-0.2.1.dist-info/WHEEL
gwkokab-0.2.1.dist-info/entry_points.txt
gwkokab-0.2.1.dist-info/top_level.txt
gwkokab-0.2.1.dist-info/RECORD
