Metadata-Version: 2.4
Name: gwkokab
Version: 0.2.1
Summary: A JAX-based gravitational-wave population inference toolkit for parametric models
Author-email: Meesum Qazalbash <meesumqazalbash@gmail.com>, Muhammad Zeeshan <m.zeeshan5885@gmail.com>, Richard O'Shaughnessy <richardoshaughnessyrossma@gmail.com>
Maintainer-email: Meesum Qazalbash <meesumqazalbash@gmail.com>
License:                                  Apache License
Project-URL: Changelog, https://github.com/gwkokab/gwkokab/blob/main/CHANGELOG.md
Project-URL: Discussion, https://github.com/gwkokab/gwkokab/discussions
Project-URL: Homepage, https://github.com/gwkokab/gwkokab
Project-URL: Issues, https://github.com/gwkokab/gwkokab/issues
Keywords: astrophysics,bayesian-inference,bbh,binary-black-holes,binary-neutron-stars,bns,compact-binaries,gravitational-waves,jax,neutron-star-black-hole,nsbh,population-inference
Classifier: Intended Audience :: Developers
Classifier: Intended Audience :: Education
Classifier: Intended Audience :: Science/Research
Classifier: License :: OSI Approved :: Apache Software License
Classifier: Operating System :: MacOS
Classifier: Operating System :: Microsoft :: Windows
Classifier: Operating System :: POSIX :: Linux
Classifier: Programming Language :: Python :: 3.11
Classifier: Programming Language :: Python :: 3.12
Classifier: Programming Language :: Python :: 3.13
Classifier: Programming Language :: Python :: 3
Requires-Python: >=3.11
License-File: LICENSE
Requires-Dist: arviz>=0.20.0
Requires-Dist: chex>=0.1.87
Requires-Dist: equinox>=0.11.3
Requires-Dist: flowMC==0.4.5
Requires-Dist: glasbey>=0.3.0
Requires-Dist: h5py>=3.12.1
Requires-Dist: jaxtyping>=0.2.36
Requires-Dist: jenkspy==0.4.1
Requires-Dist: loguru>=0.7.0
Requires-Dist: matplotlib>=3.9.0
Requires-Dist: mplcursors>=0.6
Requires-Dist: numpy<3
Requires-Dist: numpyro>=0.19.0
Requires-Dist: pandas>=2.2.0
Requires-Dist: quadax>=0.2.5
Requires-Dist: RIFT>=0.0.15.11
Requires-Dist: scipy>=1.12
Requires-Dist: seaborn>=0.13.0
Requires-Dist: tqdm>=4.60.0
Provides-Extra: cpu
Requires-Dist: jax<0.9.0,>=0.4.30; extra == "cpu"
Provides-Extra: cuda12
Requires-Dist: jax[cuda12]<0.9.0,>=0.4.30; extra == "cuda12"
Provides-Extra: cuda13
Requires-Dist: jax[cuda13]<0.9.0,>=0.4.30; extra == "cuda13"
Provides-Extra: tpu
Requires-Dist: jax[tpu]<0.9.0,>=0.4.30; extra == "tpu"
Provides-Extra: dev
Requires-Dist: pre-commit>=4.0.0; extra == "dev"
Requires-Dist: ruff>=0.8.0; extra == "dev"
Requires-Dist: setuptools>=75.6.0; extra == "dev"
Provides-Extra: test
Requires-Dist: pytest>=8.3.0; extra == "test"
Requires-Dist: tfp-nightly; extra == "test"
Requires-Dist: astropy>=6.0.0; extra == "test"
Provides-Extra: doc
Requires-Dist: astroid<5; extra == "doc"
Requires-Dist: furo; extra == "doc"
Requires-Dist: ipython!=8.7.0; extra == "doc"
Requires-Dist: myst-nb; extra == "doc"
Requires-Dist: setuptools_scm; extra == "doc"
Requires-Dist: sphinx_design; extra == "doc"
Requires-Dist: sphinx-autoapi; extra == "doc"
Requires-Dist: sphinx-copybutton; extra == "doc"
Requires-Dist: sphinx-togglebutton; extra == "doc"
Requires-Dist: sphinx>=2.0; extra == "doc"
Requires-Dist: sphinxcontrib-bibtex; extra == "doc"
Dynamic: license-file
